P4WorkspaceCreator/WorkspaceCreator.py
P4WorkspaceCreator/__init__.py
P4WorkspaceCreator/__main__.py
P4WorkspaceCreator-1.0.3.dist-info/LICENSE
P4WorkspaceCreator-1.0.3.dist-info/METADATA
P4WorkspaceCreator-1.0.3.dist-info/WHEEL
P4WorkspaceCreator-1.0.3.dist-info/top_level.txt
P4WorkspaceCreator-1.0.3.dist-info/RECORD
