Metadata-Version: 2.1
Name: P4WorkspaceCreator
Version: 1.0.3
Summary: Create perforce workspace from the spec file
Home-page: https://github.com/sachinrising/p4-workspace-creator
Author: sachin srivastava
Author-email: sachinsasr@gmail.com
Project-URL: Bug Tracker, https://github.com/sachinrising/p4-workspace-creator/issues
Classifier: Programming Language :: Python :: 3.5
Classifier: Programming Language :: Python :: 3.6
Classifier: Programming Language :: Python :: 3.7
Classifier: Programming Language :: Python :: 3.8
Classifier: Programming Language :: Python :: 3.9
Classifier: Programming Language :: Python :: 3.10
Classifier: Programming Language :: Python :: 3.11
Classifier: Programming Language :: Python :: 3.12
Classifier: License :: OSI Approved :: MIT License
Classifier: Operating System :: OS Independent
Requires-Python: <3.13,>=3.5
License-File: LICENSE
Requires-Dist: P4Python
